neutrino/torch.cpython-36m-x86_64-linux-gnu.so
neutrino/framework/torch_primitives.cpython-36m-x86_64-linux-gnu.so
neutrino/framework/torch_surgeon.cpython-36m-x86_64-linux-gnu.so
neutrino/framework/torch_data_loader.cpython-36m-x86_64-linux-gnu.so
neutrino/framework/torch_model.cpython-36m-x86_64-linux-gnu.so
neutrino/framework/torch_nn.cpython-36m-x86_64-linux-gnu.so
neutrino/framework/torch_extension.cpython-36m-x86_64-linux-gnu.so
neutrino/framework/torch_distributed.cpython-36m-x86_64-linux-gnu.so
neutrino/framework/torch_quantization.cpython-36m-x86_64-linux-gnu.so
neutrino/framework/torch_framework.cpython-36m-x86_64-linux-gnu.so
neutrino/framework/torch_graph.cpython-36m-x86_64-linux-gnu.so
neutrino_torch-1.3.3.dist-info/METADATA
neutrino_torch-1.3.3.dist-info/RECORD
neutrino_torch-1.3.3.dist-info/top_level.txt
neutrino_torch-1.3.3.dist-info/LICENSE
neutrino_torch-1.3.3.dist-info/WHEEL
thirdparty/torch_surgery/__init__.cpython-36m-x86_64-linux-gnu.so
thirdparty/torch_surgery/structured.cpython-36m-x86_64-linux-gnu.so
thirdparty/torch_surgery/dependency.cpython-36m-x86_64-linux-gnu.so
