Metadata-Version: 2.1
Name: neutrino-torch
Version: 1.3.3
Summary: Torch backend for Deeplite Neutrino engine.
Home-page: https://www.deeplite.ai
Author: Deeplite
Author-email: support@deeplite.ai
License: Proprietary
Keywords: optimizer deep_neural_network deep_learning neural_architecture_search torch
Platform: UNKNOWN
Classifier: Development Status :: 5 - Production/Stable
Classifier: Intended Audience :: Science/Research
Classifier: Intended Audience :: Developers
Classifier: Programming Language :: Python
Classifier: Programming Language :: Python :: 3.6
Classifier: Programming Language :: Python :: 3.7
Classifier: Programming Language :: Python :: 3.8
Classifier: Programming Language :: Python :: Implementation :: CPython
Classifier: Topic :: Scientific/Engineering :: Artificial Intelligence
Classifier: Topic :: Software Development :: Libraries :: Python Modules
Classifier: Operating System :: POSIX :: Linux
Classifier: Natural Language :: English
Classifier: License :: Other/Proprietary License
Classifier: Environment :: Console
Requires-Dist: neutrino-engine (>=5.3.0)
Requires-Dist: torch (<=1.8.1,>=1.4)
Requires-Dist: deeplite-profiler[torch]
Requires-Dist: deeplite-model-converter[torch]
Requires-Dist: Augmentor (==0.2.8)
